homeautomation/__init__.py
homeautomation/devices.py
homeautomation/helpfuncs.py
homeautomation/kostal_plenticore.py
homeautomation/kostal_sem.py
homeautomation/start.py
homeautomation/datamodel/__init__.py
homeautomation/datamodel/modbus.py
gkj_homeautomation-0.1.1.dist-info/METADATA
gkj_homeautomation-0.1.1.dist-info/WHEEL
gkj_homeautomation-0.1.1.dist-info/entry_points.txt
gkj_homeautomation-0.1.1.dist-info/RECORD
